{
  "appPageId" : "555d77a1-8ee9-4e6c-87f0-c8b241724ee2",
  "componentName" : "siteforce:sldsOneColLayout",
  "dataProviders" : [ ],
  "id" : "6b3af909-2866-44a3-b17e-712af65afdb9",
  "label" : "Stream List",
  "regions" : [ {
    "components" : [ {
      "componentAttributes" : { },
      "componentName" : "forceCommunity:streamList",
      "id" : "1699e499-806b-4c17-8576-a3b913604b4c",
      "renderPriority" : "NEUTRAL",
      "renditionMap" : { },
      "type" : "component"
    } ],
    "id" : "e6672e54-c904-4f89-acf3-6b51c28a47c0",
    "regionName" : "content",
    "type" : "region"
  } ],
  "themeLayoutType" : "Inner",
  "type" : "view",
  "viewType" : "list-0Fq"
}