{
  "appPageId" : "555d77a1-8ee9-4e6c-87f0-c8b241724ee2",
  "componentName" : "siteforce:sldsOneColLayout",
  "dataProviders" : [ ],
  "id" : "457a5656-9503-442b-b23c-ceeeafa2206d",
  "label" : "Topic Catalog",
  "regions" : [ {
    "components" : [ {
      "componentAttributes" : {
        "bannerText" : "",
        "bannerTextWithKnowledge" : "Explore other <a href=\"javascript:void(0)\" class=\"headlineArticles\">articles</a> and <a href=\"javascript:void(0)\" class=\"headlineDiscussions\">discussions</a> on this topic.",
        "bannerTextWithoutKnowledge" : "Explore other <a href=\"javascript:void(0)\" class=\"headlineDiscussions\">discussions</a> on this topic.",
        "pageType" : "",
        "showSubTopics" : true,
        "title" : "Topics",
        "uniqueNameOrId" : ""
      },
      "componentName" : "forceCommunity:headline",
      "id" : "f710c6b9-3460-4ef0-b939-b51029917b46",
      "renderPriority" : "NEUTRAL",
      "renditionMap" : { },
      "type" : "component"
    } ],
    "id" : "051e0cbb-2a82-47d8-bcac-be9913c248a1",
    "regionName" : "header",
    "type" : "region"
  }, {
    "components" : [ {
      "componentAttributes" : { },
      "componentName" : "forceCommunity:topicCatalog",
      "id" : "4467ccb9-0032-4a3d-8b36-2770bc829a8e",
      "renderPriority" : "NEUTRAL",
      "renditionMap" : { },
      "type" : "component"
    } ],
    "id" : "b8a1de6c-d06d-4572-8fbe-1147f306d23d",
    "regionName" : "content",
    "type" : "region"
  }, {
    "components" : [ {
      "componentAttributes" : {
        "askCommunityLabel" : "Ask a Question",
        "buttonBgColor" : "",
        "buttonBgHoverColor" : "",
        "buttonBorderColor" : "",
        "buttonRadius" : 0,
        "buttonTextColor" : "",
        "buttonTextHoverColor" : "",
        "buttonTwoBgColor" : "",
        "buttonTwoBgHoverColor" : "",
        "buttonTwoBorderColor" : "",
        "buttonTwoRadius" : 0,
        "buttonTwoTextColor" : "",
        "buttonTwoTextHoverColor" : "",
        "confirmationMessage" : "Got it!",
        "contactSupportLabel" : "Contact Support",
        "followUpPromptLabel" : "Can we close your question?",
        "headerLabel" : "Don't see what you're looking for?",
        "isAskFollowPromptEnabled" : true,
        "isIncludeArticlesEnabled" : false,
        "isIncludeDiscussionsEnabled" : true,
        "isInitialSatisfactionPromptEnabled" : true,
        "isPublisherDeflectionEnabled" : true,
        "maxSuggestions" : 5,
        "satisfactionPromptLabel" : "Did we help to answer your question?",
        "showDetails" : false,
        "showTopics" : true
      },
      "componentName" : "siteforce:napiliFooter",
      "id" : "8f7d4a41-2d87-484b-a7ef-a8bfae24f294",
      "renderPriority" : "NEUTRAL",
      "renditionMap" : { },
      "type" : "component"
    } ],
    "id" : "d05b663c-f8ba-4399-a8dd-fa759d4e9f3e",
    "regionName" : "footer",
    "type" : "region"
  }, {
    "components" : [ {
      "componentAttributes" : {
        "customHeadTags" : "",
        "description" : "",
        "title" : "Topic Catalog"
      },
      "componentName" : "forceCommunity:seoAssistant",
      "id" : "0c1b7725-1183-4918-807f-c6edcd76c882",
      "renditionMap" : { },
      "type" : "component"
    } ],
    "id" : "e291c727-090d-4c2f-9979-db39a00f13fe",
    "regionName" : "sfdcHiddenRegion",
    "type" : "region"
  } ],
  "themeLayoutType" : "Inner",
  "type" : "view",
  "viewType" : "topic-catalog"
}